prusa2mqtt/__init__.py
prusa2mqtt/main.py
prusa2mqtt-0.4.dist-info/LICENSE
prusa2mqtt-0.4.dist-info/METADATA
prusa2mqtt-0.4.dist-info/WHEEL
prusa2mqtt-0.4.dist-info/entry_points.txt
prusa2mqtt-0.4.dist-info/top_level.txt
prusa2mqtt-0.4.dist-info/RECORD
