Metadata-Version: 2.1
Name: prusa2mqtt
Version: 0.4
Summary: Command line tool that parses the USB serial output of a Prusa printer and publishes the sensor values and progress to an MQTT server.
Home-page: https://github.com/vindolin/prusa2mqtt
Author: Thomas Schüßler
License: MIT
Keywords: 3d printing,serial,prusa,mqtt
Platform: UNKNOWN
Classifier: Development Status :: 4 - Beta
Classifier: License :: OSI Approved :: MIT License
Classifier: Programming Language :: Python :: 3.8
License-File: LICENSE
Requires-Dist: paho-mqtt (==1.6.1)
Requires-Dist: pyserial (==3.5)
